---
layout:     post
title:      "ASM介绍"
subtitle:   ""
date:       2021-08-08 12:00:00
author:     "Yaku"
header-img: "img/post-bg-2015.jpg"
tags:
    - Java
    - ASM
---



# 1.class文件格式

官方文档：https://docs.oracle.com/javase/specs/jvms/se8/html/jvms-4.html

```Plain
ClassFile {
    u4             magic; // 魔数，CAFEBABE
    u2             minor_version; // 副版本号
    u2             major_version; // 主版本号
    u2             constant_pool_count; // 常量池
    cp_info        constant_pool[constant_pool_count-1];
    u2             access_flags; // 类访问标记
    u2             this_class; // 类索引
    u2             super_class; // 父类索引
    u2             interfaces_count; // 实现接口数量
    u2             interfaces[interfaces_count]; // 接口索引
    u2             fields_count; // 成员变量
    field_info     fields[fields_count];
    u2             methods_count; // 方法
    method_info    methods[methods_count];
    u2             attributes_count; // 属性
    attribute_info attributes[attributes_count];
}
```



## 1.1 常量池

| **Constant Type**           | **Value** | **cp_info**                                                  |
| --------------------------- | --------- | ------------------------------------------------------------ |
| CONSTANT_Class              | 7         | CONSTANT_Class_info {    u1 tag;    u2 name_index; }         |
| CONSTANT_Fieldref           | 9         | CONSTANT_Fieldref_info {    u1 tag;    u2 class_index;    u2 name_and_type_index; } |
| CONSTANT_Methodref          | 10        | CONSTANT_Methodref_info {    u1 tag;    u2 class_index;    u2 name_and_type_index; } |
| CONSTANT_InterfaceMethodref | 11        | CONSTANT_InterfaceMethodref_info {    u1 tag;    u2 class_index;    u2 name_and_type_index; } |
| CONSTANT_String             | 8         | CONSTANT_String_info {    u1 tag;    u2 string_index; }      |
| CONSTANT_Integer            | 3         | CONSTANT_Integer_info {    u1 tag;    u4 bytes; }            |
| CONSTANT_Float              | 4         | CONSTANT_Float_info {    u1 tag;    u4 bytes; }              |
| CONSTANT_Long               | 5         | CONSTANT_Long_info {    u1 tag;    u4 high_bytes;    u4 low_bytes; } |
| CONSTANT_Double             | 6         | CONSTANT_Double_info {    u1 tag;    u4 high_bytes;    u4 low_bytes; } |
| CONSTANT_NameAndType        | 12        | CONSTANT_NameAndType_info {    u1 tag;    u2 name_index;    u2 descriptor_index; } |
| CONSTANT_Utf8               | 1         | CONSTANT_Utf8_info {    u1 tag;    u2 length;    u1 bytes[length]; } |
| CONSTANT_MethodHandle       | 15        | CONSTANT_MethodHandle_info {    u1 tag;    u1 reference_kind;    u2 reference_index; } |
| CONSTANT_MethodType         | 16        | CONSTANT_MethodType_info {    u1 tag;    u2 descriptor_index; } |
| CONSTANT_InvokeDynamic      | 18        | CONSTANT_InvokeDynamic_info {    u1 tag;    u2 bootstrap_method_attr_index;    u2 name_and_type_index; } |



## 1.2 成员变量

```Plain
field_info {
    u2             access_flags;
    u2             name_index;
    u2             descriptor_index;
    u2             attributes_count;
    attribute_info attributes[attributes_count];
}
```

access_flags常量：

| **Flag Name** | **Value** | **Interpretation**                                           |
| ------------- | --------- | ------------------------------------------------------------ |
| ACC_PUBLIC    | 0x0001    | Declared public; may be accessed from outside its package.   |
| ACC_PRIVATE   | 0x0002    | Declared private; usable only within the defining class.     |
| ACC_PROTECTED | 0x0004    | Declared protected; may be accessed within subclasses.       |
| ACC_STATIC    | 0x0008    | Declared static.                                             |
| ACC_FINAL     | 0x0010    | Declared final; never directly assigned to after object construction (JLS §17.5). |
| ACC_VOLATILE  | 0x0040    | Declared volatile; cannot be cached.                         |
| ACC_TRANSIENT | 0x0080    | Declared transient; not written or read by a persistent object manager. |
| ACC_SYNTHETIC | 0x1000    | Declared synthetic; not present in the source code.          |
| ACC_ENUM      | 0x4000    | Declared as an element of an enum.                           |



## 1.3 方法

```Plain
method_info {
    u2             access_flags;
    u2             name_index;
    u2             descriptor_index;
    u2             attributes_count;
    attribute_info attributes[attributes_count];
}
```

access_flags常量：

| **Flag Name**    | **Value** | **Interpretation**                                           |
| ---------------- | --------- | ------------------------------------------------------------ |
| ACC_PUBLIC       | 0x0001    | Declared public; may be accessed from outside its package.   |
| ACC_PRIVATE      | 0x0002    | Declared private; accessible only within the defining class. |
| ACC_PROTECTED    | 0x0004    | Declared protected; may be accessed within subclasses.       |
| ACC_STATIC       | 0x0008    | Declared static.                                             |
| ACC_FINAL        | 0x0010    | Declared final; must not be overridden ([§5.4.5](https://docs.oracle.com/javase/specs/jvms/se8/html/jvms-5.html#jvms-5.4.5)). |
| ACC_SYNCHRONIZED | 0x0020    | Declared synchronized; invocation is wrapped by a monitor use. |
| ACC_BRIDGE       | 0x0040    | A bridge method, generated by the compiler.                  |
| ACC_VARARGS      | 0x0080    | Declared with variable number of arguments.                  |
| ACC_NATIVE       | 0x0100    | Declared native; implemented in a language other than Java.  |
| ACC_ABSTRACT     | 0x0400    | Declared abstract; no implementation is provided.            |
| ACC_STRICT       | 0x0800    | Declared strictfp; floating-point mode is FP-strict.         |
| ACC_SYNTHETIC    | 0x1000    | Declared synthetic; not present in the source code.          |



## 1.4 属性

```Plain
attribute_info {
    u2 attribute_name_index;
    u4 attribute_length;
    u1 info[attribute_length];
}
```

| **Attribute**                        |                                                              |
| ------------------------------------ | ------------------------------------------------------------ |
| ConstantValue                        | ConstantValue_attribute {    u2 attribute_name_index;    u4 attribute_length;    u2 constantvalue_index; } |
| Code                                 | Code_attribute {    u2 attribute_name_index;    u4 attribute_length;    u2 max_stack;    u2 max_locals;    u4 code_length;    u1 code[code_length];    u2 exception_table_length;    {   u2 start_pc;        u2 end_pc;        u2 handler_pc;        u2 catch_type;    } exception_table[exception_table_length];    u2 attributes_count;    attribute_info attributes[attributes_count]; } |
| StackMapTable                        | StackMapTable_attribute {    u2              attribute_name_index;    u4              attribute_length;    u2              number_of_entries;    stack_map_frame entries[number_of_entries]; }union stack_map_frame {    same_frame;    same_locals_1_stack_item_frame;    same_locals_1_stack_item_frame_extended;    chop_frame;    same_frame_extended;    append_frame;    full_frame; } |
| Exceptions                           | Exceptions_attribute {    u2 attribute_name_index;    u4 attribute_length;    u2 number_of_exceptions;    u2 exception_index_table[number_of_exceptions]; } |
| InnerClasses                         | InnerClasses_attribute {    u2 attribute_name_index;    u4 attribute_length;    u2 number_of_classes;    {   u2 inner_class_info_index;        u2 outer_class_info_index;        u2 inner_name_index;        u2 inner_class_access_flags;    } classes[number_of_classes]; } |
| EnclosingMethod                      | EnclosingMethod_attribute {    u2 attribute_name_index;    u4 attribute_length;    u2 class_index;    u2 method_index; } |
| Synthetic                            | Synthetic_attribute {    u2 attribute_name_index;    u4 attribute_length; } |
| Signature                            | Signature_attribute {    u2 attribute_name_index;    u4 attribute_length;    u2 signature_index; } |
| SourceFile                           | SourceFile_attribute {    u2 attribute_name_index;    u4 attribute_length;    u2 sourcefile_index; } |
| SourceDebugExtension                 | SourceDebugExtension_attribute {    u2 attribute_name_index;    u4 attribute_length;    u1 debug_extension[attribute_length]; } |
| LineNumberTable                      | LineNumberTable_attribute {    u2 attribute_name_index;    u4 attribute_length;    u2 line_number_table_length;    {   u2 start_pc;        u2 line_number;            } line_number_table[line_number_table_length]; } |
| LocalVariableTable                   | LocalVariableTable_attribute {    u2 attribute_name_index;    u4 attribute_length;    u2 local_variable_table_length;    {   u2 start_pc;        u2 length;        u2 name_index;        u2 descriptor_index;        u2 index;    } local_variable_table[local_variable_table_length]; } |
| LocalVariableTypeTable               | LocalVariableTypeTable_attribute {    u2 attribute_name_index;    u4 attribute_length;    u2 local_variable_type_table_length;    {   u2 start_pc;        u2 length;        u2 name_index;        u2 signature_index;        u2 index;    } local_variable_type_table[local_variable_type_table_length]; } |
| Deprecated                           | Deprecated_attribute {    u2 attribute_name_index;    u4 attribute_length; } |
| RuntimeVisibleAnnotations            | RuntimeVisibleAnnotations_attribute {    u2         attribute_name_index;    u4         attribute_length;    u2         num_annotations;    annotation annotations[num_annotations]; } |
| RuntimeInvisibleAnnotations          | RuntimeVisibleParameterAnnotations_attribute {    u2 attribute_name_index;    u4 attribute_length;    u1 num_parameters;    {   u2         num_annotations;        annotation annotations[num_annotations];    } parameter_annotations[num_parameters]; } |
| RuntimeVisibleParameterAnnotations   | RuntimeInvisibleParameterAnnotations_attribute {    u2 attribute_name_index;    u4 attribute_length;    u1 num_parameters;    {   u2         num_annotations;        annotation annotations[num_annotations];    } parameter_annotations[num_parameters]; } |
| RuntimeInvisibleParameterAnnotations | RuntimeVisibleTypeAnnotations_attribute {    u2              attribute_name_index;    u4              attribute_length;    u2              num_annotations;    type_annotation annotations[num_annotations]; } |
| RuntimeVisibleTypeAnnotations        | RuntimeVisibleTypeAnnotations_attribute {    u2              attribute_name_index;    u4              attribute_length;    u2              num_annotations;    type_annotation annotations[num_annotations]; } |
| RuntimeInvisibleTypeAnnotations      | RuntimeInvisibleTypeAnnotations_attribute {    u2              attribute_name_index;    u4              attribute_length;    u2              num_annotations;    type_annotation annotations[num_annotations]; } |
| AnnotationDefault                    | AnnotationDefault_attribute {    u2            attribute_name_index;    u4            attribute_length;    element_value default_value; } |
| BootstrapMethods                     | BootstrapMethods_attribute {    u2 attribute_name_index;    u4 attribute_length;    u2 num_bootstrap_methods;    {   u2 bootstrap_method_ref;        u2 num_bootstrap_arguments;        u2 bootstrap_arguments[num_bootstrap_arguments];    } bootstrap_methods[num_bootstrap_methods]; } |
| MethodParameters                     | MethodParameters_attribute {    u2 attribute_name_index;    u4 attribute_length;    u1 parameters_count;    {   u2 name_index;        u2 access_flags;    } parameters[parameters_count]; } |



## 1.5 示例

编译Java Source文件：javac HelloWorld.java

```Java
public class HelloWorld {
    public static void main(String[] args) {
        System.out.println("hello world!");
    }
}
```

查看生成的HelloWorld.class：javap -v HelloWorld.class

```Shell
Classfile HelloWorld.class
  Last modified xxxx年xx月xx日; size 426 bytes
  SHA-256 checksum 8b43cff4f88db3935ba70c5fc84b6a3e5247bcd669f82e64654424a1c1251ef1
  Compiled from "HelloWorld.java"
public class HelloWorld
  minor version: 0
  major version: 61
  flags: (0x0021) ACC_PUBLIC, ACC_SUPER
  this_class: #21                         // HelloWorld
  super_class: #2                         // java/lang/Object
  interfaces: 0, fields: 0, methods: 2, attributes: 1
Constant pool:
   #1 = Methodref          #2.#3          // java/lang/Object."<init>":()V
   #2 = Class              #4             // java/lang/Object
   #3 = NameAndType        #5:#6          // "<init>":()V
   #4 = Utf8               java/lang/Object
   #5 = Utf8               <init>
   #6 = Utf8               ()V
   #7 = Fieldref           #8.#9          // java/lang/System.out:Ljava/io/PrintStream;
   #8 = Class              #10            // java/lang/System
   #9 = NameAndType        #11:#12        // out:Ljava/io/PrintStream;
  #10 = Utf8               java/lang/System
  #11 = Utf8               out
  #12 = Utf8               Ljava/io/PrintStream;
  #13 = String             #14            // hello world!
  #14 = Utf8               hello world!
  #15 = Methodref          #16.#17        // java/io/PrintStream.println:(Ljava/lang/String;)V
  #16 = Class              #18            // java/io/PrintStream
  #17 = NameAndType        #19:#20        // println:(Ljava/lang/String;)V
  #18 = Utf8               java/io/PrintStream
  #19 = Utf8               println
  #20 = Utf8               (Ljava/lang/String;)V
  #21 = Class              #22            // HelloWorld
  #22 = Utf8               HelloWorld
  #23 = Utf8               Code
  #24 = Utf8               LineNumberTable
  #25 = Utf8               main
  #26 = Utf8               ([Ljava/lang/String;)V
  #27 = Utf8               SourceFile
  #28 = Utf8               HelloWorld.java
{
  public HelloWorld();
    descriptor: ()V
    flags: (0x0001) ACC_PUBLIC
    Code:
      stack=1, locals=1, args_size=1
         0: aload_0
         1: invokespecial #1                  // Method java/lang/Object."<init>":()V
         4: return
      LineNumberTable:
        line 1: 0

  public static void main(java.lang.String[]);
    descriptor: ([Ljava/lang/String;)V
    flags: (0x0009) ACC_PUBLIC, ACC_STATIC
    Code:
      stack=2, locals=1, args_size=1
         0: getstatic     #7                  // Field java/lang/System.out:Ljava/io/PrintStream;
         3: ldc           #13                 // String hello world!
         5: invokevirtual #15                 // Method java/io/PrintStream.println:(Ljava/lang/String;)V
         8: return
      LineNumberTable:
        line 3: 0
        line 4: 8
}
SourceFile: "HelloWorld.java"
```



# 2.字节码指令

Java虚拟机采用基于栈的架构，其指令由操作码和操作数组成。

- 操作码：一个字节长度(0~255)，意味着指令集的操作码个数不能操作256条。
- 操作数：一条指令可以有零或者多个操作数，且操作数可以是1个或者多个字节。编译后的代码没有采用操作数长度对齐方式，比如16位无符号整数需使用两个字节储存(假设为byte1和byte2)，那么真实值是 (byte1 << 8) | byte2。

大多数指令包含了其操作所对应的数据类型信息，比如iload，表示从局部变量表中加载int型的数据到操作数栈；而fload表示加载float型数据到操作数栈。由于操作码长度只有1Byte，因此Java虚拟机的指令集对于特定操作只提供有限的类型相关指令，并非为每一种数据类型都有相应的操作指令。必要时，有些指令可用于将不支持的类型转换为可被支持的类型。



## 2.1 栈操作相关指令

### xload和xstore (x可为i,l,f,d,a)

- load 命令：用于将局部变量表的指定位置的相应类型变量加载到栈顶；
- store命令：用于将栈顶的相应类型数据保入局部变量表的指定位置；

### xconst、xpush和ldc (x可为i,l,f,d,a)

- const、push：将相应类型的常量放入栈顶
- ldc:则是从常量池中将常量

### pop和dup

- pop用于栈顶数值出栈操作；
- dup用于赋值栈顶的指定个数的数值，并将其压入栈顶指定次数；



## 2.2 对象相关

### 字段调用

| 字段调用  | 含义                             |
| --------- | -------------------------------- |
| getstatic | 获取类的静态字段，将其值压入栈顶 |
| putstatic | 给类的静态字段赋值               |
| getfield  | 获取对象的字段，将其值压入栈顶   |
| putfield  | 给对象的字段赋值                 |

### 方法调用

| 方法调用        | 作用               | 解释                                   |
| --------------- | ------------------ | -------------------------------------- |
| invokevirtual   | 调用实例方法       | 虚方法分派                             |
| invokestatic    | 调用类方法         | static方法                             |
| invokeinterface | 调用接口方法       | 运行时搜索合适方法调用                 |
| invokespecial   | 调用特殊实例方法   | 包括实例初始化方法、父类方法           |
| invokedynamic   | 由用户引导方法决定 | 运行时动态解析出调用点限定符所引用方法 |

### 方法返回

| 方法返回 | 含义               |
| -------- | ------------------ |
| ireturn  | 当前方法返回int    |
| lreturn  | 当前方法返回long   |
| freturn  | 当前方法返回float  |
| dreturn  | 当前方法返回double |
| areturn  | 当前方法返回ref    |

### 对象和数组

- 创建类实例： new
- 创建数组：newarray、anewarray、multianewarray
- 数组元素 加载到 操作数栈：xaload (x可为i,l,f,d,a,b,c,s)
- 操作数栈的值 存储到数组元素： xastore (x可为i,l,f,d,a,b,c,s)
- 数组长度：arraylength
- 类实例类型：instanceof、checkcast



## 2.3 运算指令

运算指令是用于对操作数栈上的两个数值进行某种运算，并把结果重新存入到操作栈顶。Java虚拟机只支持整型和浮点型两类数据的运算指令，所有指令如下：

| 运算 | int  | long | float | double |
| ---- | ---- | ---- | ----- | ------ |
| 加法 | iadd | ladd | fadd  | dadd   |
| 减法 | isub | lsub | fsub  | dsub   |
| 乘法 | imul | lmul | fmul  | dmul   |
| 除法 | idiv | ldiv | fdiv  | ddiv   |
| 求余 | irem | lrem | frem  | drem   |
| 取反 | ineg | lneg | fneg  | dneg   |

其他运算：

- 位移：ishl,ishr,iushr,lshl,lshr,lushr
- 按位或： ior,lor
- 按位与： iand, land
- 按位异或： ixor, lxor
- 自增：iin
- 比较：dcmpg,dcmpl,fcmpg,fcmpl,lcmp



## 2.4 类型转换

类型转换用于将两种不同类型的数值进行转换。

1. 对于宽化类型转换(小范围向大范围转换)，无需显式的转换指令，并且是安全的操作。各种范围从小到大依次排序： int, long, float, double。
2. 对于窄化类型转换，必须显式地调用类型转换指令，并且该过程很可能导致精度丢失。转换规则中需要特别注意的是当浮点值为NaN, 则转换结果为int或long的0。虽然窄化运算可能会发生上/下限溢出和精度丢失等情况，但虚拟机规范明确规定窄化转换U不可能导致虚拟机抛出异常。

类型转换指令：i2b, i2c,f2i等等。



## 2.5 流程控制

控制指令是指有条件或无条件地修改PC寄存器的值，从而达到控制流程的目标

- 条件分支：ifeq、iflt、ifnull、ifnonnull等
- 复合分支：tableswitch、lookupswitch
- 无条件分支：goto、goto_w、jsr、jsr_w、ret



## 2.6 同步与异常

- 异常

Java程序显式抛出异常： athrow指令。在Java虚拟机中，处理异常(catch语句)不是由字节码指令来实现，而是采用异常表来完成。

- 同步

方法级的同步和方法内部分代码的同步，都是依靠管程(Monitor)来实现的。

Java语言使用synchronized语句块，那么Java虚拟机的指令集中通过monitorenter和monitorexit两条指令来完成synchronized的功能。为了保证monitorenter和monitorexit指令一定能成对的调用（不管方法正常结束还是异常结束），编译器会自动生成一个异常处理器，该异常处理器的主要目的是用于执行monitorexit指令。



# 3.ASM介绍

ASM 库提供了两个用于生成和转换已编译class的 API：

- 核心 API，以基于事件的形式来表示类
- 树 API，以基于对象的形式来表示类。

| 包名                            | 功能                                                         |
| ------------------------------- | ------------------------------------------------------------ |
| org.objectweb.asm               | 基于事件的 API，提供 ClassReader 和 ClassWriter 类读写Java字节码文件。 |
| org.objectweb.asm.signature     | 读写泛型签名。                                               |
| org.objectweb.asm.tree          | 基于对象的 API，提供了一些工具，用于在基于事件和基于对象的表示方法之间进行转换。 |
| org.objectweb.asm.tree.analysis | 以树 API 为基础，提供了一个类分析框架和几个预定义的类分析器。 |
| org.objectweb.asm.commons       | 提供了一些很有用的基于核心包和tree包的预定义adapters。       |
| org.objectweb.asm.util          | 提供各种基于核心 API 的工具，可以在开发和调试 ASM 应用程序时使用。 |

 

## 3.1 核心API

| 类            | 说明                                                         |
| ------------- | ------------------------------------------------------------ |
| ClassReader   | 解析class文件，调用ClassVisitor中对应的visit成员变量、方法和字节码指令方法。 |
| ClassVisitor  | 方法调用顺序：visit [ visitSource ] [ visitModule ][ visitNestHost ][ visitOuterClass ] ( visitAnnotation \| visitTypeAnnotation \| visitAttribute )* ( visitNestMember \| [ * visitPermittedSubclass ] \| visitInnerClass \| visitRecordComponent \| visitField \| visitMethod )* visitEnd. |
| ClassWriter   | 继承自ClassVisitor，生成class文件。                          |
| FieldVisitor  | 方法调用顺序： ( visitAnnotation \| visitTypeAnnotation \| visitAttribute )* visitEnd. |
| FieldWriter   | 继承自FieldVisitor。                                         |
| MethodVisitor | 方法调用顺序： ( visitParameter )* [ visitAnnotationDefault ] ( visitAnnotation \| visitAnnotableParameterCount \| visitParameterAnnotation visitTypeAnnotation \| visitAttribute )* [ visitCode ( visitFrame \| visit<i>X</i>Insn \| visitLabel \| visitInsnAnnotation \| visitTryCatchBlock \| visitTryCatchAnnotation \| visitLocalVariable \| visitLocalVariableAnnotation \| visitLineNumber )* visitMaxs ] visitEnd. |
| MethodWriter  | 继承自MethodVisitor                                          |



## 3.2 树API

AbstractInsnNode是一个抽象类，表示字节码指令的节点。其子类有：

| 节点                   | opcode                                                       |
| ---------------------- | ------------------------------------------------------------ |
| FieldInsnNode          | GETSTATIC, PUTSTATIC, GETFIELD or PUTFIELD.                  |
| FrameNode              | -1                                                           |
| IincInsnNode           | IINC                                                         |
| InsnNode               | NOP, ACONST_NULL, ICONST_M1, ICONST_0, ICONST_1, ICONST_2, ICONST_3, ICONST_4, ICONST_5, LCONST_0, LCONST_1, FCONST_0, FCONST_1, FCONST_2, DCONST_0, DCONST_1, IALOAD, LALOAD, FALOAD, DALOAD, AALOAD, BALOAD, CALOAD, SALOAD, IASTORE, LASTORE, FASTORE, DASTORE, AASTORE, BASTORE, CASTORE, SASTORE, POP, POP2, DUP, DUP_X1, DUP_X2, DUP2, DUP2_X1, DUP2_X2, SWAP, IADD, LADD, FADD, DADD, ISUB, LSUB, FSUB, DSUB, IMUL, LMUL, FMUL, DMUL, IDIV, LDIV, FDIV, DDIV, IREM, LREM, FREM, DREM, INEG, LNEG, FNEG, DNEG, ISHL, LSHL, ISHR, LSHR, IUSHR, LUSHR, IAND, LAND, IOR, LOR, IXOR, LXOR, I2L, I2F, I2D, L2I, L2F, L2D, F2I, F2L, F2D, D2I, D2L, D2F, I2B, I2C, I2S, LCMP, FCMPL, FCMPG, DCMPL, DCMPG, IRETURN, LRETURN, FRETURN, DRETURN, ARETURN, RETURN, ARRAYLENGTH, ATHROW, MONITORENTER, or MONITOREXIT. |
| IntInsnNode            | BIPUSH, SIPUSH or NEWARRAY.                                  |
| InvokeDynamicInsnNode  | INVOKEDYNAMIC                                                |
| JumpInsnNode           | IFEQ, IFNE, IFLT, IFGE, IFGT, IFLE, IF_ICMPEQ, IF_ICMPNE, IF_ICMPLT, IF_ICMPGE, IF_ICMPGT, IF_ICMPLE, IF_ACMPEQ, IF_ACMPNE, GOTO, JSR, IFNULL or IFNONNULL. |
| LabelNode              | -1                                                           |
| LdcInsnNode            | LDC                                                          |
| LineNumberNode         | -1                                                           |
| LookupSwitchInsnNode   | LOOKUPSWITCH                                                 |
| MethodInsnNode         | INVOKEVIRTUAL, INVOKESPECIAL, INVOKESTATIC or INVOKEINTERFACE. |
| MultiANewArrayInsnNode | MULTIANEWARRAY                                               |
| TableSwitchInsnNode    | TABLESWITCH                                                  |
| TypeInsnNode           | NEW, ANEWARRAY, CHECKCAST or INSTANCEOF.                     |
| VarInsnNode            | ILOAD, LLOAD, FLOAD, DLOAD, ALOAD, ISTORE, LSTORE, FSTORE, DSTORE, ASTORE or RET. |

其他节点：

| 节点                        |                                      |
| --------------------------- | ------------------------------------ |
| AnnotationNode              | 继承自AnnotationVisitor，注解节点。  |
| ClassNode                   | 继承自ClassVisitor，类节点。         |
| FieldNode                   | 继承自FieldVisitor，类成员变量节点。 |
| InnerClassNode              | 内部类节点。                         |
| LocalVariableAnnotationNode | 继承自TypeAnnotationNode。           |
| LocalVariableNode           | 局部变量声明节点。                   |
| MethodNode                  | 方法节点。                           |
| ParameterNode               | 方法参数节点。                       |
| RecordComponentNode         | 继承自RecordComponentVisitor。       |
| TryCatchBlockNode           | try-catch代码块节点。                |
| TypeAnnotationNode          | 继承自TypeAnnotationNode             |